cecs/__init__.py
cecs/command_line.py
cecs/icfDevelopment.py
cecs/menu stuff.py
cecs/text.py
cecs-0.1.dev1.dist-info/DESCRIPTION.rst
cecs-0.1.dev1.dist-info/METADATA
cecs-0.1.dev1.dist-info/RECORD
cecs-0.1.dev1.dist-info/WHEEL
cecs-0.1.dev1.dist-info/metadata.json
cecs-0.1.dev1.dist-info/top_level.txt
