Metadata-Version: 2.0
Name: cecs
Version: 0.1.dev1
Summary: Cisco Enterprise Cloud Suite
Home-page: https://github.com/clijockey/CECS
Author: clijockey
Author-email: rob.j.edwards@gmail.com
License: MIT
Keywords: cecs ucsd icfb cisco
Platform: UNKNOWN
Classifier: Development Status :: 3 - Alpha
Classifier: License :: OSI Approved :: MIT License
Classifier: Programming Language :: Python :: 2.7
Requires-Dist: colorama
Requires-Dist: json
Requires-Dist: markdown
Requires-Dist: requests
